rabbit_broker/__init__.py
rabbit_broker/models.py
rabbit_broker/schemas.py
rabbit_broker/settings.py
rabbit_broker/async_chains/__init__.py
rabbit_broker/async_chains/base.py
rabbit_broker/chains/__init__.py
rabbit_broker/chains/base.py
rabbit_broker/queues/__init__.py
rabbit_broker/queues/base.py
rabbit_broker/queues/models.py
rabbit_broker/queues/persistent.py
rabbit_broker/queues/rabbitmq.py
rabbit_broker/services/__init__.py
rabbit_broker/services/base.py
rabbit_broker/utils/__init__.py
rabbit_broker/utils/singleton.py
simple_rabbit_broker-0.0.3.dist-info/METADATA
simple_rabbit_broker-0.0.3.dist-info/WHEEL
simple_rabbit_broker-0.0.3.dist-info/licenses/LICENSE
simple_rabbit_broker-0.0.3.dist-info/RECORD
